README.md
setup.py
aiopm/_PostmarkClient.py
aiopm/__init__.py
aiopm.egg-info/PKG-INFO
aiopm.egg-info/SOURCES.txt
aiopm.egg-info/dependency_links.txt
aiopm.egg-info/requires.txt
aiopm.egg-info/top_level.txt